README.md
setup.py
cloudera/__init__.py
cloudera/director/__init__.py
cloudera/director/common/__init__.py
cloudera/director/common/client.py
cloudera/director/common/configuration.py
cloudera/director/common/rest.py
cloudera/director/common/versions_api.py
cloudera/director/common/models/__init__.py
cloudera/director/common/models/version.py
cloudera/director/d6_0/__init__.py
cloudera/director/d6_0/authentication_api.py
cloudera/director/d6_0/clusters_api.py
cloudera/director/d6_0/database_servers_api.py
cloudera/director/d6_0/deployments_api.py
cloudera/director/d6_0/environments_api.py
cloudera/director/d6_0/eula_api.py
cloudera/director/d6_0/import_client_config_api.py
cloudera/director/d6_0/instance_templates_api.py
cloudera/director/d6_0/notifications_api.py
cloudera/director/d6_0/provider_metadata_api.py
cloudera/director/d6_0/server_config_api.py
cloudera/director/d6_0/users_api.py
cloudera/director/d6_0/models/__init__.py
cloudera/director/d6_0/models/capabilities.py
cloudera/director/d6_0/models/cloud_provider_metadata.py
cloudera/director/d6_0/models/cluster.py
cloudera/director/d6_0/models/cluster_administration_settings.py
cloudera/director/d6_0/models/cluster_template.py
cloudera/director/d6_0/models/cluster_update_event_summary.py
cloudera/director/d6_0/models/configuration_property.py
cloudera/director/d6_0/models/configuration_property_value.py
cloudera/director/d6_0/models/deployment.py
cloudera/director/d6_0/models/deployment_template.py
cloudera/director/d6_0/models/diagnostic_data_summary.py
cloudera/director/d6_0/models/display_property.py
cloudera/director/d6_0/models/environment.py
cloudera/director/d6_0/models/error_info.py
cloudera/director/d6_0/models/eula.py
cloudera/director/d6_0/models/external_account.py
cloudera/director/d6_0/models/external_database.py
cloudera/director/d6_0/models/external_database_server.py
cloudera/director/d6_0/models/external_database_server_template.py
cloudera_director_python_client.egg-info/PKG-INFO
cloudera_director_python_client.egg-info/SOURCES.txt
cloudera_director_python_client.egg-info/dependency_links.txt
cloudera_director_python_client.egg-info/requires.txt
cloudera_director_python_client.egg-info/top_level.txt