Metadata-Version: 1.0
Name: cloudera-director-python-client
Version: 6.2.0.1
Summary: Cloudera Altus Director API
Home-page: UNKNOWN
Author: UNKNOWN
Author-email: UNKNOWN
License: UNKNOWN
Keywords: Swagger,Cloudera Altus Director API
Platform: UNKNOWN
